skyant/stub.py
skyant-0.0.2.dist-info/LICENSE
skyant-0.0.2.dist-info/METADATA
skyant-0.0.2.dist-info/WHEEL
skyant-0.0.2.dist-info/top_level.txt
skyant-0.0.2.dist-info/RECORD
