Metadata-Version: 2.1
Name: skyant
Version: 0.0.2
Summary: Cloud Application Framework
Home-page: https://skyant.dev
Author: Iurii Tarasenko
Author-email: info@skyant.dev
License: MIT
Project-URL: Source & issues, https://gitlab.com/skyant/python/shell
Project-URL: Documentation, https://docs.skyant.dev/projects/shell
Keywords: grpc,rest,api,dash,cloud application
Classifier: Programming Language :: Python :: 3.10
Classifier: Intended Audience :: Developers
Classifier: Intended Audience :: Information Technology
Classifier: Topic :: Software Development :: Libraries :: Python Modules
Requires-Python: >=3.10
License-File: LICENSE
